[
  {
    "id": "3jEpiw87n5U",
    "title": "Subway surfer gameplay no commentary",
    "duration": 688,
    "url": "https://www.youtube.com/watch?v=3jEpiw87n5U"
  },
  {
    "id": "zZ7AimPACzc",
    "title": "Subway surfers 1 hour Gameplay no commentary free to use",
    "duration": 3579,
    "url": "https://www.youtube.com/watch?v=zZ7AimPACzc"
  },
  {
    "id": "vTfD20dbxho",
    "title": "2 Hour Compilation Subway Surfers Gameplay / Subway Surf /2024/ Play ON PC Subway Surfer HD",
    "duration": 7575,
    "url": "https://www.youtube.com/watch?v=vTfD20dbxho"
  },
  {
    "id": "L_fcrOyoWZ8",
    "title": "Compilation PlayGame Subway Surfers / Subway Surf /2023/ On PC Non Stop 1 Hour HD",
    "duration": 4017,
    "url": "https://www.youtube.com/watch?v=L_fcrOyoWZ8"
  },
  {
    "id": "7ghSziUQnhs",
    "title": "Subway Surfers (2023) - Gameplay (PC UHD) [4K60FPS]",
    "duration": 2364,
    "url": "https://www.youtube.com/watch?v=7ghSziUQnhs"
  },
  {
    "id": "W2Qvg6XkxGs",
    "title": "Subway surfers 1 hour Gameplay no commentary free to use",
    "duration": 3690,
    "url": "https://www.youtube.com/watch?v=W2Qvg6XkxGs"
  },
  {
    "id": "t5YuEYISF_o",
    "title": "Brawl Stars x Subway Surfers - Gameplay Walkthrough - No Commentary (iOS Android) - 4K UHD",
    "duration": 699,
    "url": "https://www.youtube.com/watch?v=t5YuEYISF_o"
  },
  {
    "id": "61oLMj28vF8",
    "title": "Subway Surfers | No Copyright Gameplay | No Commentary & Sound | HD 4K",
    "duration": 772,
    "url": "https://www.youtube.com/watch?v=61oLMj28vF8"
  },
  {
    "id": "hyPAx2mCQh4",
    "title": "Watch the ultimate Subway Surfer action\u2014no distractions, just pure, high-speed runs. \ud83d\ude31 1080p",
    "duration": 2826,
    "url": "https://www.youtube.com/watch?v=hyPAx2mCQh4"
  },
  {
    "id": "i6TI1BpZs50",
    "title": "Subway surfers gameplay 11 (no commentary)",
    "duration": 290,
    "url": "https://www.youtube.com/watch?v=i6TI1BpZs50"
  },
  {
    "id": "Xo16J6fT1bE",
    "title": "Subway Surfers 4K ULTRA HD Gameplay | No Commentary | Copyright-Free",
    "duration": 556,
    "url": "https://www.youtube.com/watch?v=Xo16J6fT1bE"
  },
  {
    "id": "eRXE8Aebp7s",
    "title": "10 hour loop playing Subway Surfers",
    "duration": 35639,
    "url": "https://www.youtube.com/watch?v=eRXE8Aebp7s"
  },
  {
    "id": "ObhmrE6FyNs",
    "title": "Subway Surfers Gameplay (PC UHD) [4K60FPS]",
    "duration": 1411,
    "url": "https://www.youtube.com/watch?v=ObhmrE6FyNs"
  },
  {
    "id": "z4FyfOkTjfo",
    "title": "5 Subway Surfers tricks to improve your gameplay (No coin challenge)",
    "duration": 33,
    "url": "https://www.youtube.com/watch?v=z4FyfOkTjfo"
  },
  {
    "id": "bI0oNDe5DLE",
    "title": "Subway Surfers Gameplay! No Commentary",
    "duration": 366,
    "url": "https://www.youtube.com/watch?v=bI0oNDe5DLE"
  },
  {
    "id": "fXCUaRE-5Rc",
    "title": "Subway Surfer... 1 hour HD 720px",
    "duration": 3909,
    "url": "https://www.youtube.com/watch?v=fXCUaRE-5Rc"
  },
  {
    "id": "oNjznyx4CMo",
    "title": "subway surf edit",
    "duration": 20,
    "url": "https://www.youtube.com/watch?v=oNjznyx4CMo"
  },
  {
    "id": "SUbwSah71Cg",
    "title": "\"Subway Surfers in 2025 Be Like . #subwaysurfers #subwaysurf #mobilegaming #mobilegameplay",
    "duration": 251,
    "url": "https://www.youtube.com/watch?v=SUbwSah71Cg"
  },
  {
    "id": "ICU06h-ETRM",
    "title": "Subway Surfers Full Gameplay \ud83c\udfae | High Score Run | No Commentary",
    "duration": 474,
    "url": "https://www.youtube.com/watch?v=ICU06h-ETRM"
  },
  {
    "id": "SFI0huL4h7E",
    "title": "the ultimate Subway Surfers betrayal #subwaysurfers",
    "duration": 21,
    "url": "https://www.youtube.com/watch?v=SFI0huL4h7E"
  },
  {
    "id": "6hRFsVXuBh4",
    "title": "Subway Surfers - GAMEPLAY - no commentary part 2",
    "duration": 169,
    "url": "https://www.youtube.com/watch?v=6hRFsVXuBh4"
  },
  {
    "id": "vMLiD1Timgk",
    "title": "ALL Brawl Stars Characters NO FLOOR Challenge \ud83c\udf0b | Subway Surfers x Brawl Stars 2025",
    "duration": 465,
    "url": "https://www.youtube.com/watch?v=vMLiD1Timgk"
  },
  {
    "id": "GrRc1pCQbCU",
    "title": "The Streets of D.C. Don\u2019t Forgive! Subway Surfers Run \ud83d\udea8\ud83c\udfc3\u200d\u2642\ufe0f",
    "duration": 482,
    "url": "https://www.youtube.com/watch?v=GrRc1pCQbCU"
  },
  {
    "id": "hF4tmwAzgow",
    "title": "High Speed Run! | Subway Surfers | Gameplay #1| No Commentary",
    "duration": 246,
    "url": "https://www.youtube.com/watch?v=hF4tmwAzgow"
  },
  {
    "id": "PV3P3n2WUaA",
    "title": "Subway Surfers Live Stream \ud83c\udf1f | No Commentary | HD Gameplay 2025",
    "duration": 5959,
    "url": "https://www.youtube.com/watch?v=PV3P3n2WUaA"
  },
  {
    "id": "i0M4ARe9v0Y",
    "title": "Subway Surfers (2024) - Gameplay [4K 16x9] No Copyright",
    "duration": 311,
    "url": "https://www.youtube.com/watch?v=i0M4ARe9v0Y"
  },
  {
    "id": "-zTcWBOy6j0",
    "title": "Subway Surfers - GAMEPLAY - no commentary",
    "duration": 94,
    "url": "https://www.youtube.com/watch?v=-zTcWBOy6j0"
  },
  {
    "id": "XOMk9yi9g6Y",
    "title": "Subway Surfers VS Subway Surfers Game \ud83c\udfae gameplay iox android",
    "duration": 199,
    "url": "https://www.youtube.com/watch?v=XOMk9yi9g6Y"
  },
  {
    "id": "UQSMXkujbIo",
    "title": "Subway surfers \u26a1 564 android gameplay #videogame #subscribe #subwaysurfers #gaming",
    "duration": 13,
    "url": "https://www.youtube.com/watch?v=UQSMXkujbIo"
  },
  {
    "id": "9A1mn6vJUvM",
    "title": "10 Minutes of Subway Surfers Gameplay (No Commentary)",
    "duration": 582,
    "url": "https://www.youtube.com/watch?v=9A1mn6vJUvM"
  },
  {
    "id": "FFM6ZqV0DBc",
    "title": "How to do invisible glitch in subway surfers#glitch #gaming #fyp #subwaysurfers #",
    "duration": 17,
    "url": "https://www.youtube.com/watch?v=FFM6ZqV0DBc"
  },
  {
    "id": "-rjeVH0yWIU",
    "title": "add friends and personalize ur profile in Subway Surfers now #subwaysurfers",
    "duration": 17,
    "url": "https://www.youtube.com/watch?v=-rjeVH0yWIU"
  },
  {
    "id": "tGgzOExbGGU",
    "title": "Subway Surfers on 2 phones is wild #subwaysurfers #subwaysurfersclassic",
    "duration": 8,
    "url": "https://www.youtube.com/watch?v=tGgzOExbGGU"
  },
  {
    "id": "wg_g028OhPE",
    "title": "Subway Surfers Guard couldn\u2019t take it anymore #subwaysurfers #invincible #omniman",
    "duration": 44,
    "url": "https://www.youtube.com/watch?v=wg_g028OhPE"
  },
  {
    "id": "V97I9e5g2Jk",
    "title": "Subway Surfers Highest Score \ud83d\ude32\ud83d\ude31\ud83d\ude02 | Subway Surfers Game \ud83c\udfae | #shorts #subwaysurfers #short",
    "duration": 8,
    "url": "https://www.youtube.com/watch?v=V97I9e5g2Jk"
  },
  {
    "id": "efX-d5PDVpM",
    "title": "Subway surfers | No Coin Challenge - Handcam \ud83d\udc80\ud83d\udd25 #subwaysurfers",
    "duration": 12,
    "url": "https://www.youtube.com/watch?v=efX-d5PDVpM"
  },
  {
    "id": "shnBGMZDJ0c",
    "title": "When you play the subway surfers reverse \ud83d\udc80",
    "duration": 13,
    "url": "https://www.youtube.com/watch?v=shnBGMZDJ0c"
  },
  {
    "id": "1sIrq1TA6hQ",
    "title": "Subway Surfers : Jake VS Ninja \ud83e\udd77 VS Prince K VS Harumi #shorts #subwaysurfers #gaming",
    "duration": 24,
    "url": "https://www.youtube.com/watch?v=1sIrq1TA6hQ"
  },
  {
    "id": "wXIPNH4ojiY",
    "title": "Subway Surfers Monaco - GAMEPLAY - no commentary part 3",
    "duration": 442,
    "url": "https://www.youtube.com/watch?v=wXIPNH4ojiY"
  },
  {
    "id": "wSpPq4LEPRo",
    "title": "I played Subway Surfers for 10 hours straight",
    "duration": 586,
    "url": "https://www.youtube.com/watch?v=wSpPq4LEPRo"
  },
  {
    "id": "Bfk_omAz3iE",
    "title": "how to get dino character in subway surfers",
    "duration": 5,
    "url": "https://www.youtube.com/watch?v=Bfk_omAz3iE"
  },
  {
    "id": "qRtNisp8fh4",
    "title": "Difficulty Impossible! || #shorts",
    "duration": 15,
    "url": "https://www.youtube.com/watch?v=qRtNisp8fh4"
  },
  {
    "id": "ygR7YIT15t4",
    "title": "Evolution Of Subway Surfers \ud83d\ude22 #subwaysurfers #evolution #nostalgia #shorts #youtubeshorts",
    "duration": 50,
    "url": "https://www.youtube.com/watch?v=ygR7YIT15t4"
  },
  {
    "id": "rQiSDSaby8o",
    "title": "Subway Surfers in real life #subwaysurfers",
    "duration": 11,
    "url": "https://www.youtube.com/watch?v=rQiSDSaby8o"
  },
  {
    "id": "OrEWq_LkpII",
    "title": "Subway Surfers High Score Chase \ud83d\ude87 | No Commentary Live Gameplay",
    "duration": 3344,
    "url": "https://www.youtube.com/watch?v=OrEWq_LkpII"
  },
  {
    "id": "qT85_7JYe54",
    "title": "Playing Subway Surfers Live! No Commentary Gameplay",
    "duration": 367,
    "url": "https://www.youtube.com/watch?v=qT85_7JYe54"
  },
  {
    "id": "vIRQChZAngI",
    "title": "Subway Surfers on scratch!! (No commentary)",
    "duration": 79,
    "url": "https://www.youtube.com/watch?v=vIRQChZAngI"
  },
  {
    "id": "Ph-dMn1Ear4",
    "title": "SPEED Just Broke the Subway Surfers WORLD RECORD! \ud83e\udd2f #shorts #ishowspeed #shortsfeed",
    "duration": 38,
    "url": "https://www.youtube.com/watch?v=Ph-dMn1Ear4"
  },
  {
    "id": "wza65cl7dak",
    "title": "the most rarest subway surfers skins",
    "duration": 8,
    "url": "https://www.youtube.com/watch?v=wza65cl7dak"
  },
  {
    "id": "MRc14ENY_Eo",
    "title": "T800 ultra me Subway Surfers kaise chalaye \ud83d\udc4d| How to use Subway Surfers in T800 ultra #viral #shorts",
    "duration": 17,
    "url": "https://www.youtube.com/watch?v=MRc14ENY_Eo"
  },
  {
    "id": "aupUIFl3S6M",
    "title": "How to do Infinite score glitch in Subway Surfers",
    "duration": 30,
    "url": "https://www.youtube.com/watch?v=aupUIFl3S6M"
  },
  {
    "id": "qQm00A4xu2Y",
    "title": "1 Minute of Subway Surfers (No Commentary)",
    "duration": 90,
    "url": "https://www.youtube.com/watch?v=qQm00A4xu2Y"
  },
  {
    "id": "l2XDInpYhUg",
    "title": "Subway Surfers in Brawl Stars Theory",
    "duration": 34,
    "url": "https://www.youtube.com/watch?v=l2XDInpYhUg"
  },
  {
    "id": "m3VMT6WDg5c",
    "title": "Subway Horror: Full Gameplay Walkthrough - Chapter 1 (No Commentary)",
    "duration": 1061,
    "url": "https://www.youtube.com/watch?v=m3VMT6WDg5c"
  },
  {
    "id": "OuaMPkt1VKw",
    "title": "Subway surfer gameplay #2 no commentary",
    "duration": 508,
    "url": "https://www.youtube.com/watch?v=OuaMPkt1VKw"
  },
  {
    "id": "Qu_0IuAvuFA",
    "title": "Subway Surfers High Score Chase \ud83d\ude87 | No Commentary Live Gameplay",
    "duration": 904,
    "url": "https://www.youtube.com/watch?v=Qu_0IuAvuFA"
  },
  {
    "id": "fKmRaqIC1kQ",
    "title": "Subway surfers (no commentary)",
    "duration": 219,
    "url": "https://www.youtube.com/watch?v=fKmRaqIC1kQ"
  },
  {
    "id": "OFQQ-EY4R5s",
    "title": "The reality of Subway Surfers (Part 3) @subwaysurfers",
    "duration": 51,
    "url": "https://www.youtube.com/watch?v=OFQQ-EY4R5s"
  },
  {
    "id": "arTW4tp--YY",
    "title": "Subway Surfers High Score Chase \ud83d\ude87 | No Commentary Live Gameplay",
    "duration": 87,
    "url": "https://www.youtube.com/watch?v=arTW4tp--YY"
  },
  {
    "id": "QFzfgB34cCk",
    "title": "Subway Surfers No Coins 5:36 WORLD RECORD",
    "duration": 345,
    "url": "https://www.youtube.com/watch?v=QFzfgB34cCk"
  },
  {
    "id": "TURr66XM64c",
    "title": "Subway surfer apk mod unlimited coin #hack #subway #surfer #coin",
    "duration": 18,
    "url": "https://www.youtube.com/watch?v=TURr66XM64c"
  },
  {
    "id": "vod0XNiKMNk",
    "title": "Winning Super Runner Jake in Subway Surfers Stage 5/5 | No commentary",
    "duration": 277,
    "url": "https://www.youtube.com/watch?v=vod0XNiKMNk"
  },
  {
    "id": "CpsNey9NMI4",
    "title": "Subway Surfers - Gameplay - No Copyright - No commentary - free to use - use for Insta or tik tok",
    "duration": 243,
    "url": "https://www.youtube.com/watch?v=CpsNey9NMI4"
  },
  {
    "id": "BaZ-tQVAVx0",
    "title": "How To Do INFINITE SCORE GLITCH In SUBWAY SURFERS!!! \ud83e\udd76\ud83e\udd2f",
    "duration": 46,
    "url": "https://www.youtube.com/watch?v=BaZ-tQVAVx0"
  },
  {
    "id": "_KutDyErAwY",
    "title": "Subway Horror Full Gameplay Walkthrough (Chapters 1 & 2) No Commentary",
    "duration": 2179,
    "url": "https://www.youtube.com/watch?v=_KutDyErAwY"
  },
  {
    "id": "U5_a38_AWLk",
    "title": "SUBWAY SURFERS NO COINS :v",
    "duration": 22,
    "url": "https://www.youtube.com/watch?v=U5_a38_AWLk"
  },
  {
    "id": "b64Fd_pJ1iE",
    "title": "Subway Surfers but RTX is ON Gameplay PC [4k\u2076\u2070\u1da0\u1d56\u02e2UHD] |No Commentary|",
    "duration": 378,
    "url": "https://www.youtube.com/watch?v=b64Fd_pJ1iE"
  },
  {
    "id": "xqIfYj2MZa8",
    "title": "Free keys!!! | (Promo code) Subway surfers",
    "duration": 17,
    "url": "https://www.youtube.com/watch?v=xqIfYj2MZa8"
  },
  {
    "id": "XSIyxtQ7grQ",
    "title": "The ENDING of Subway Surfers REVEALED \ud83e\udd2f\u200b #shorts",
    "duration": 12,
    "url": "https://www.youtube.com/watch?v=XSIyxtQ7grQ"
  },
  {
    "id": "U5bYUfrlf2c",
    "title": "Subway Surfers| Gameplay| Walkthrough| No Commentary| Part-1|",
    "duration": 984,
    "url": "https://www.youtube.com/watch?v=U5bYUfrlf2c"
  },
  {
    "id": "qErc1bzEwmA",
    "title": "Playing Subway Surfers Live! No Commentary Gameplay",
    "duration": 3655,
    "url": "https://www.youtube.com/watch?v=qErc1bzEwmA"
  },
  {
    "id": "FxwpQHl452s",
    "title": "Where to go to put in the redeem code in Subway Surfer",
    "duration": 19,
    "url": "https://www.youtube.com/watch?v=FxwpQHl452s"
  },
  {
    "id": "WoqZTsIsW8w",
    "title": "Add me as a Friend in Subway Surfers #subway #subwaysurfers #subwaysurf #games #gaming #gameplay",
    "duration": 18,
    "url": "https://www.youtube.com/watch?v=WoqZTsIsW8w"
  },
  {
    "id": "09cNPyPMCts",
    "title": "Subway Surfer no commentary gameplay with lofi hiphop beats",
    "duration": 1667,
    "url": "https://www.youtube.com/watch?v=09cNPyPMCts"
  },
  {
    "id": "WvrQCpWYBBk",
    "title": "Subway Surfers But in RTX ON | PARIS",
    "duration": 73,
    "url": "https://www.youtube.com/watch?v=WvrQCpWYBBk"
  },
  {
    "id": "phiXqc4xdno",
    "title": "Updated  Subway Surfers \ud83d\ude80\ud83d\udca5\ud83d\udcaf\ud83e\udd2c | like & subscribe | #subwaysurfers #gaming #trending #games #shorts",
    "duration": 130,
    "url": "https://www.youtube.com/watch?v=phiXqc4xdno"
  },
  {
    "id": "m631_bkqglE",
    "title": "How To Friend Request || subway surf add firands #friends #subwaysurfers",
    "duration": 15,
    "url": "https://www.youtube.com/watch?v=m631_bkqglE"
  },
  {
    "id": "Iec_OIoRQtY",
    "title": "Playing Subway Surfers Live! No Commentary Gameplay",
    "duration": 3863,
    "url": "https://www.youtube.com/watch?v=Iec_OIoRQtY"
  },
  {
    "id": "3Q7FLNkKZdc",
    "title": "I Played Subway Surfer AGAIN After a Long Time. No Commentary Gameplay.",
    "duration": 1709,
    "url": "https://www.youtube.com/watch?v=3Q7FLNkKZdc"
  },
  {
    "id": "qTnluQhtuOc",
    "title": "Subway Surfers | Android Gameplay #Shorts #SubwaySurfers",
    "duration": 51,
    "url": "https://www.youtube.com/watch?v=qTnluQhtuOc"
  },
  {
    "id": "qx-xUZvPo7I",
    "title": "#subwaysurfers #gaming #shorts #shortsfeed #games #trendingshorts #ytshorts",
    "duration": 25,
    "url": "https://www.youtube.com/watch?v=qx-xUZvPo7I"
  },
  {
    "id": "uMyJxCHCEis",
    "title": "Subway Surfers No Commentary #1",
    "duration": 479,
    "url": "https://www.youtube.com/watch?v=uMyJxCHCEis"
  },
  {
    "id": "arTW4tp--YY",
    "title": "Subway Surfers High Score Chase \ud83d\ude87 | No Commentary Live Gameplay",
    "duration": 87,
    "url": "https://www.youtube.com/watch?v=arTW4tp--YY"
  },
  {
    "id": "7m9qhzDMQao",
    "title": "Subway Surfers Greece | like & subscribe | subway surfers (Day 23) | No Commentary Gameplay .......",
    "duration": 331,
    "url": "https://www.youtube.com/watch?v=7m9qhzDMQao"
  },
  {
    "id": "EyMz-sowrnU",
    "title": "Subway SURF NIKOS vs KING vs Jack #gaming2025 #subwaysurfers #runchallenge  #brawlstars #gameplay",
    "duration": 29,
    "url": "https://www.youtube.com/watch?v=EyMz-sowrnU"
  },
  {
    "id": "CRacic6Wvkw",
    "title": "Subway Surfer Game|| Subway Surfer Gameplay|| Android Gameplay|| No Commentary||",
    "duration": 209,
    "url": "https://www.youtube.com/watch?v=CRacic6Wvkw"
  },
  {
    "id": "NrUU1DGnjYw",
    "title": "Fortnite Chapter 2 Creative: Subway Surfers Parkour Adventure Map Full Gameplay No Commentary",
    "duration": 208,
    "url": "https://www.youtube.com/watch?v=NrUU1DGnjYw"
  },
  {
    "id": "eMmfd5YPDjo",
    "title": "New Character Unlocked \ud83d\udd13 ||#shorts",
    "duration": 6,
    "url": "https://www.youtube.com/watch?v=eMmfd5YPDjo"
  },
  {
    "id": "PJ69qAnjmQA",
    "title": "Subway Surfers No Copyright Gameplay FOR TIKTOK & YOUTUBE No Commentary Free To Use #8",
    "duration": 276,
    "url": "https://www.youtube.com/watch?v=PJ69qAnjmQA"
  },
  {
    "id": "HNIIc5ARfZg",
    "title": "Subway Surfers No Copyright Gameplay FOR TIKTOK & YOUTUBE No Commentary Free To Use #7",
    "duration": 1112,
    "url": "https://www.youtube.com/watch?v=HNIIc5ARfZg"
  },
  {
    "id": "xeaP4Xs6r-c",
    "title": "SUBWAY SURF VERY AMAZING GAME#youtubeshorts #subwaysurfers #ytshorts",
    "duration": 7,
    "url": "https://www.youtube.com/watch?v=xeaP4Xs6r-c"
  },
  {
    "id": "P0CRsNJkKyg",
    "title": "Hardest trick in no coin challenge Subway Surfers #2 #nocoinchallenge",
    "duration": 22,
    "url": "https://www.youtube.com/watch?v=P0CRsNJkKyg"
  },
  {
    "id": "qkZwSpe4QI0",
    "title": "Subway Surfers Kid got what he deserves! #invincible #subwaysurfers",
    "duration": 54,
    "url": "https://www.youtube.com/watch?v=qkZwSpe4QI0"
  },
  {
    "id": "yiQVYCrh3j4",
    "title": "Subway Surfers \ud83c\udfc4\u200d\u2640\ufe0f #trending\u200b #subwaysurfers\u200b #gaming\u200b #games\u200b #shortsfeed\u200b",
    "duration": 11,
    "url": "https://www.youtube.com/watch?v=yiQVYCrh3j4"
  },
  {
    "id": "CeTakrbe3QQ",
    "title": "subway surfers shorts funn video #shorts #trending #gaming #surfers #subwaysurfers",
    "duration": 17,
    "url": "https://www.youtube.com/watch?v=CeTakrbe3QQ"
  },
  {
    "id": "D03Uxv7EwjY",
    "title": "Subway Surfers@subwaymetrotracks  Mumbai Pc jake gameplay  #shortsfeed #shorts",
    "duration": 12,
    "url": "https://www.youtube.com/watch?v=D03Uxv7EwjY"
  },
  {
    "id": "Z9AQwL7fV1g",
    "title": "Subway surfers part23|ending point",
    "duration": 25,
    "url": "https://www.youtube.com/watch?v=Z9AQwL7fV1g"
  },
  {
    "id": "PGz6f4p5hZU",
    "title": "Pure Gameplay in the D.C. Subway System \u2013 No Commentary \ud83c\udfae\ud83d\udee4\ufe0f",
    "duration": 492,
    "url": "https://www.youtube.com/watch?v=PGz6f4p5hZU"
  },
  {
    "id": "AgHE2KGYFVY",
    "title": "Subway surfers game \ud83c\udfae  (2025 Jake-01 #viral #subwaysurfers #shorts #victoryanthem",
    "duration": 29,
    "url": "https://www.youtube.com/watch?v=AgHE2KGYFVY"
  },
  {
    "id": "x5CA6vD7h5c",
    "title": "Subway Surfers No Copyright Gameplay FOR TIKTOK & YOUTUBE No Commentary Free To Use #6",
    "duration": 2244,
    "url": "https://www.youtube.com/watch?v=x5CA6vD7h5c"
  },
  {
    "id": "15dO0znCpDU",
    "title": "Subway Surfers Game Live \ud83c\udfae Long Gameplay No Commentary",
    "duration": 282,
    "url": "https://www.youtube.com/watch?v=15dO0znCpDU"
  },
  {
    "id": "AjeHifGmf6Q",
    "title": "Subway Surfers LIVE | No Commentary | Chill Gameplay",
    "duration": 3923,
    "url": "https://www.youtube.com/watch?v=AjeHifGmf6Q"
  },
  {
    "id": "maxMYlO0k9M",
    "title": "Subway Surfers | Android Gameplay #3 #Shorts #SubwaySurfers",
    "duration": 56,
    "url": "https://www.youtube.com/watch?v=maxMYlO0k9M"
  },
  {
    "id": "kQdxpJxYdMY",
    "title": "What's your favorite Ps4 game?",
    "duration": 19,
    "url": "https://www.youtube.com/watch?v=kQdxpJxYdMY"
  },
  {
    "id": "FYCba7K1StE",
    "title": "Subway Surfers No Copyright Gameplay FOR TIKTOK & YOUTUBE No Commentary Free To Use #9",
    "duration": 853,
    "url": "https://www.youtube.com/watch?v=FYCba7K1StE"
  },
  {
    "id": "KZWogGy030Q",
    "title": "Brawl stars gameplay (No commentary)",
    "duration": 1691,
    "url": "https://www.youtube.com/watch?v=KZWogGy030Q"
  },
  {
    "id": "z8GxEm1bn-U",
    "title": "Subway Surfers Part 2 | Old Is Gold Nostalgia \ud83d\ude0d | Best Mobile Game Ever | #Shorts",
    "duration": 42,
    "url": "https://www.youtube.com/watch?v=z8GxEm1bn-U"
  },
  {
    "id": "qI4_VcWY3cM",
    "title": "Playing Subway Surfers Live! No Commentary Gameplay",
    "duration": 3688,
    "url": "https://www.youtube.com/watch?v=qI4_VcWY3cM"
  },
  {
    "id": "uXXbLdIguDI",
    "title": "Roblox is scary af, I'm telling you \ud83d\ude28",
    "duration": 26,
    "url": "https://www.youtube.com/watch?v=uXXbLdIguDI"
  },
  {
    "id": "oArUMJYnKv4",
    "title": "Subway Surfers LIVE | No Commentary | Chill Gameplay",
    "duration": 2762,
    "url": "https://www.youtube.com/watch?v=oArUMJYnKv4"
  },
  {
    "id": "kxwK_Hh8-Xs",
    "title": "worlds highest Score Record in subway surfers #shorts #games #viral #shortsvideo #subwaysurfers",
    "duration": 52,
    "url": "https://www.youtube.com/watch?v=kxwK_Hh8-Xs"
  },
  {
    "id": "wSjNLmvTPiE",
    "title": "Subway Surfers: 1 HOUR of INSANE Gameplay! (No Breaks) #subwaysurfers #1HourGameplay #mobilegaming",
    "duration": 1964,
    "url": "https://www.youtube.com/watch?v=wSjNLmvTPiE"
  },
  {
    "id": "KZHXVoqtb7c",
    "title": "Subway Surfers Gameplay \ud83c\udfc3\u200d\u2642 No Copyright Gameplay \ud83c\udfc3\u200d\u2642 #subwaysurfers #gaming @Mixrootgaming  clip 5",
    "duration": 125,
    "url": "https://www.youtube.com/watch?v=KZHXVoqtb7c"
  },
  {
    "id": "V4I9GHNFnBU",
    "title": "subway princess runner no collect coins #shorts #like #comment #subscribe",
    "duration": 15,
    "url": "https://www.youtube.com/watch?v=V4I9GHNFnBU"
  },
  {
    "id": "-i0OIy5zSrs",
    "title": "Subway Surfers Gameplay PC - BEST Games",
    "duration": 866,
    "url": "https://www.youtube.com/watch?v=-i0OIy5zSrs"
  },
  {
    "id": "8zk6YiItYPU",
    "title": "Subway surfers 5 min Gameplay no commentary new chartered %#viral #subscribe #subwaysurfs #video",
    "duration": 61,
    "url": "https://www.youtube.com/watch?v=8zk6YiItYPU"
  },
  {
    "id": "kNztlw0mIWU",
    "title": "i made world record in Subway surfers",
    "duration": 33,
    "url": "https://www.youtube.com/watch?v=kNztlw0mIWU"
  },
  {
    "id": "FCBKURZFuog",
    "title": "Subway surf amezing very awesome game#youtubeshorts #trending #shortssubway #shorts #viral",
    "duration": 5,
    "url": "https://www.youtube.com/watch?v=FCBKURZFuog"
  },
  {
    "id": "uGmvHRDPM8o",
    "title": "Subway Surfer handcam mobile #handcan #subwaysurfers #shorts",
    "duration": 11,
    "url": "https://www.youtube.com/watch?v=uGmvHRDPM8o"
  },
  {
    "id": "OqPxaKs8xrk",
    "title": "3 Hour Parkour with Shaders in Minecraft (No Falls, Relaxing, Sleep)",
    "duration": 10955,
    "url": "https://www.youtube.com/watch?v=OqPxaKs8xrk"
  },
  {
    "id": "Hb-7QjB7TCI",
    "title": "\ud83d\udd34Subway Surfers Live Chill Stream | Road To 1000 Subs | No Commentary",
    "duration": 1586,
    "url": "https://www.youtube.com/watch?v=Hb-7QjB7TCI"
  },
  {
    "id": "HTMDNZOlUq4",
    "title": "Subway Surfers But in Unreal Engine 5",
    "duration": 69,
    "url": "https://www.youtube.com/watch?v=HTMDNZOlUq4"
  },
  {
    "id": "Ey4h7IV-w_0",
    "title": "New Character Unlocked \ud83d\udd13 | Ninja |#shorts",
    "duration": 9,
    "url": "https://www.youtube.com/watch?v=Ey4h7IV-w_0"
  },
  {
    "id": "73S8ElNhx9g",
    "title": "Playing Subway Surfers Live! No Commentary Gameplay",
    "duration": 827,
    "url": "https://www.youtube.com/watch?v=73S8ElNhx9g"
  },
  {
    "id": "BQMIBRPc0jw",
    "title": "Playing Subway Surfers Live! No Commentary Gameplay",
    "duration": 3764,
    "url": "https://www.youtube.com/watch?v=BQMIBRPc0jw"
  },
  {
    "id": "wSpPq4LEPRo",
    "title": "I played Subway Surfers for 10 hours straight",
    "duration": 586,
    "url": "https://www.youtube.com/watch?v=wSpPq4LEPRo"
  },
  {
    "id": "QdouJak-GDE",
    "title": "SUBWAY SURFERS \ud83c\udfc4\u200d\u2642\ufe0f #viral #gameplay #subwaysurfer #shortvideo #viralreels #shortsvideo #viralpage",
    "duration": 9,
    "url": "https://www.youtube.com/watch?v=QdouJak-GDE"
  },
  {
    "id": "N775RUK1agA",
    "title": "The Secret Pokemon Black and White Ending \ud83d\ude32 #shorts",
    "duration": 35,
    "url": "https://www.youtube.com/watch?v=N775RUK1agA"
  },
  {
    "id": "5T3x8jeLbbA",
    "title": "Subway Surfers Gameplay Walkthrough Part 3 (Android/iOS)",
    "duration": 720,
    "url": "https://www.youtube.com/watch?v=5T3x8jeLbbA"
  },
  {
    "id": "nW6plRRdRq4",
    "title": "Playing Subway Surfers Live! No Commentary Gameplay",
    "duration": 3787,
    "url": "https://www.youtube.com/watch?v=nW6plRRdRq4"
  },
  {
    "id": "VnrwqgSZTVQ",
    "title": "Evolution of Subway Surfers Games 2012-2022 (No Commentary)",
    "duration": 515,
    "url": "https://www.youtube.com/watch?v=VnrwqgSZTVQ"
  },
  {
    "id": "c99ZZNULDR0",
    "title": "FLOOR IS LAVA  #gaming2025 #subwaysurfers #runchallenge",
    "duration": 30,
    "url": "https://www.youtube.com/watch?v=c99ZZNULDR0"
  },
  {
    "id": "l_tbYCIl_Jo",
    "title": "Every one hate this in subway surfers | #shorts #viral #shortsvideo #subwaysurfers #games",
    "duration": 51,
    "url": "https://www.youtube.com/watch?v=l_tbYCIl_Jo"
  },
  {
    "id": "lJWJh2mfWXY",
    "title": "Subway surfers 'M' alphabet edits | (Song PERFECT) | #perfect",
    "duration": 24,
    "url": "https://www.youtube.com/watch?v=lJWJh2mfWXY"
  },
  {
    "id": "Mq3J4bhVB8w",
    "title": "Subway Surfers No Copyright Gameplay FOR TIKTOK & YOUTUBE No Commentary Free To Use #4",
    "duration": 1149,
    "url": "https://www.youtube.com/watch?v=Mq3J4bhVB8w"
  },
  {
    "id": "fg7HwBwYBvw",
    "title": "SUBWAY SURFERS GAMEPLAY \ud83d\ude31\ud83d\ude31\ud83d\ude31 #subwaysurfers #virel  #shortsyoutubevideo \u2764\ufe0f\u2764\ufe0f\u2764\ufe0f #bdsumitgaming",
    "duration": 13,
    "url": "https://www.youtube.com/watch?v=fg7HwBwYBvw"
  },
  {
    "id": "8_EeAy73bLM",
    "title": "Subway Surfers World Tour New City Beijing Gameplay #1 - Android No Commentary Game",
    "duration": 351,
    "url": "https://www.youtube.com/watch?v=8_EeAy73bLM"
  },
  {
    "id": "HzbmlNkClV4",
    "title": "Subway Surfers |  Gameplay Walkthrough Part 1 - Playing With The Tricky (IOS & Android) #Shorts",
    "duration": 59,
    "url": "https://www.youtube.com/watch?v=HzbmlNkClV4"
  },
  {
    "id": "8tP0cOIYgaw",
    "title": "Granny gameplay (No commentary) Part 1",
    "duration": 353,
    "url": "https://www.youtube.com/watch?v=8tP0cOIYgaw"
  },
  {
    "id": "pb-JElkXiXw",
    "title": "Subway Surfers Gameplay Walkthrough Part 1 (Android/iOS)",
    "duration": 730,
    "url": "https://www.youtube.com/watch?v=pb-JElkXiXw"
  },
  {
    "id": "Opw_x96FYXU",
    "title": "Playing Subway Surfers Live! No Commentary Gameplay",
    "duration": 4041,
    "url": "https://www.youtube.com/watch?v=Opw_x96FYXU"
  },
  {
    "id": "8vQYU3vw4F0",
    "title": "Subway Surfers Gameplay Walkthrough Part 2 (Android/iOS)",
    "duration": 842,
    "url": "https://www.youtube.com/watch?v=8vQYU3vw4F0"
  },
  {
    "id": "SI3f-gwMUc4",
    "title": "Subway surfers live stream | No Commentary | Mallu streamer",
    "duration": 3451,
    "url": "https://www.youtube.com/watch?v=SI3f-gwMUc4"
  },
  {
    "id": "dHaNlMJceWY",
    "title": "Plants VS Zombies Nostalgia\ud83d\ude14",
    "duration": 17,
    "url": "https://www.youtube.com/watch?v=dHaNlMJceWY"
  },
  {
    "id": "A_Z53o8tQRk",
    "title": "Subway Surfers Gameplay",
    "duration": 30,
    "url": "https://www.youtube.com/watch?v=A_Z53o8tQRk"
  },
  {
    "id": "pVdx3fN2q2s",
    "title": "Subway Surfers LIVE | No Commentary | Chill Gameplay",
    "duration": 1589,
    "url": "https://www.youtube.com/watch?v=pVdx3fN2q2s"
  },
  {
    "id": "0yvubF8mBok",
    "title": "How to download subway surfers hack (unlimited keys+coins)",
    "duration": 15,
    "url": "https://www.youtube.com/watch?v=0yvubF8mBok"
  },
  {
    "id": "bxFR5FEv6L4",
    "title": "SUBWAY SURF PRINCESS RUNNING TO MUCH #youtubeshorts #viral #shorts",
    "duration": 5,
    "url": "https://www.youtube.com/watch?v=bxFR5FEv6L4"
  },
  {
    "id": "d3UrnbrJFv8",
    "title": "Teleporter Vs Bouncer Board Challenge Subway surfers",
    "duration": 15,
    "url": "https://www.youtube.com/watch?v=d3UrnbrJFv8"
  },
  {
    "id": "2nHc51Xk5mo",
    "title": "Subwas Surfers Love? How to surf on hoverboard? SHORT",
    "duration": 60,
    "url": "https://www.youtube.com/watch?v=2nHc51Xk5mo"
  },
  {
    "id": "Oh2UQYi5qf8",
    "title": "Playing Subway Surfers Live! No Commentary Gameplay",
    "duration": 4369,
    "url": "https://www.youtube.com/watch?v=Oh2UQYi5qf8"
  },
  {
    "id": "4gFhtAn0N0A",
    "title": "Plant \u2618\ufe0f Invasion No Floor Challenge \ud83c\udf0b | High Jump & Running Skills | Subway Surfers",
    "duration": 42,
    "url": "https://www.youtube.com/watch?v=4gFhtAn0N0A"
  },
  {
    "id": "FUv6dKgSVhQ",
    "title": "no floor challenge in Subway surfers if you like comment it and subscribe my channel for more videos",
    "duration": 180,
    "url": "https://www.youtube.com/watch?v=FUv6dKgSVhQ"
  },
  {
    "id": "P24Kgz8gHLo",
    "title": "Subway Surfers - Miss Maia - Gameplay Part 16 (IOS, Andriod) #shorts",
    "duration": 30,
    "url": "https://www.youtube.com/watch?v=P24Kgz8gHLo"
  },
  {
    "id": "cM4WYLODAZ8",
    "title": "Subway Surfers\ud83d\ude87 || New update \ud83d\ude0d\ud83d\udd25|| 2025- 28 may || #subwaysurfers #shorts #short",
    "duration": 15,
    "url": "https://www.youtube.com/watch?v=cM4WYLODAZ8"
  },
  {
    "id": "7NI6ZoVXeJ0",
    "title": "No title only gameplay. #subway #gaming #viralvideos #games like comment and subscribe \ud83d\ude0d\ud83e\udd70\ud83d\ude18",
    "duration": 17,
    "url": "https://www.youtube.com/watch?v=7NI6ZoVXeJ0"
  },
  {
    "id": "1HUGvkhBHqE",
    "title": "Subway Surfers Full Gameplay \u2013 Endless Run (Long Video)\u201d",
    "duration": 90,
    "url": "https://www.youtube.com/watch?v=1HUGvkhBHqE"
  },
  {
    "id": "uLcoQSydRi0",
    "title": "Subway Surfers\ud83d\ude87 || New update \ud83d\ude0d\ud83d\udd25|| 2025-17 may || #subwaysurfers #shorts #short",
    "duration": 16,
    "url": "https://www.youtube.com/watch?v=uLcoQSydRi0"
  },
  {
    "id": "DutrzEoodjA",
    "title": "Subway Surfers Gameplay Walkthrough Part 5 (Android/iOS)",
    "duration": 1171,
    "url": "https://www.youtube.com/watch?v=DutrzEoodjA"
  },
  {
    "id": "cl8UESAzbQA",
    "title": "SUBWAY SURF \ud83c\udfc4\u200d\u2640\ufe0f \ud83c\udf0a \ud83d\ude0b \ud83d\ude0d \ud83d\udc4c \ud83c\udfc4\u200d\u2642\ufe0f #gaming #viralpage #game #gameplay #subwaysurfer #game #shortsvideo",
    "duration": 11,
    "url": "https://www.youtube.com/watch?v=cl8UESAzbQA"
  },
  {
    "id": "pMpjRzxceOo",
    "title": "Subway Surfers portrayed by minecraft... #Shorts",
    "duration": 27,
    "url": "https://www.youtube.com/watch?v=pMpjRzxceOo"
  },
  {
    "id": "3MO0SQA9Tws",
    "title": "SUBWAY SURF SLAP \ud83c\udfc4\u200d\u2640\ufe0f \ud83c\udf0a \ud83d\ude0b #gaming  #viralpage #game #gameplay  #shortvideo #shortsvideo #viral",
    "duration": 10,
    "url": "https://www.youtube.com/watch?v=3MO0SQA9Tws"
  },
  {
    "id": "xQ_0OiuGJHU",
    "title": "Subway Surfers vs Cat Runner (No Commentary) #catrunner #subwaysurfers",
    "duration": 48,
    "url": "https://www.youtube.com/watch?v=xQ_0OiuGJHU"
  },
  {
    "id": "x4oGX4c7Rpc",
    "title": "Subway Surfers All Levels Gameplay #Shorts",
    "duration": 17,
    "url": "https://www.youtube.com/watch?v=x4oGX4c7Rpc"
  },
  {
    "id": "0LjTulY6Wzw",
    "title": "subway surfers\ud83d\ude87 new game #shorts #trending #gaming #subwaysurfers",
    "duration": 17,
    "url": "https://www.youtube.com/watch?v=0LjTulY6Wzw"
  },
  {
    "id": "q8tXF9pKrt0",
    "title": "Temple Run Gameplay | High Score Challenge | No Commentary | Android Game #androidgamers #mobilegame",
    "duration": 60,
    "url": "https://www.youtube.com/watch?v=q8tXF9pKrt0"
  },
  {
    "id": "NC1_vDI9tiA",
    "title": "subway surfers new video no coins challenge #trending",
    "duration": 15,
    "url": "https://www.youtube.com/watch?v=NC1_vDI9tiA"
  },
  {
    "id": "kqMivjx-HW8",
    "title": "Subway surfers part29| ending point",
    "duration": 16,
    "url": "https://www.youtube.com/watch?v=kqMivjx-HW8"
  },
  {
    "id": "zvfn9FPokuk",
    "title": "Subway surfers New Gameplay | Subway surfers High Score Hd Gameplay....\ud83c\udfc3\ud83d\ude87#shorts",
    "duration": 39,
    "url": "https://www.youtube.com/watch?v=zvfn9FPokuk"
  },
  {
    "id": "f2HaUCA-JPo",
    "title": "subway surfers new video no coins challenge #trending #gaming",
    "duration": 14,
    "url": "https://www.youtube.com/watch?v=f2HaUCA-JPo"
  },
  {
    "id": "eASgM1mTxJQ",
    "title": "\ud83d\udeab No Power-Up Challenge in Subway Surfers \ud83c\udfc3\u200d\u2642\ufe0f#subwaysurfers #challenge #gaming #mobilegaming",
    "duration": 32,
    "url": "https://www.youtube.com/watch?v=eASgM1mTxJQ"
  },
  {
    "id": "h4_AEybOuAY",
    "title": "Subway Surfers\ud83d\ude87\ud83c\udfc3Gameplay walkthrough Android,ios #gameplay #shorts",
    "duration": 43,
    "url": "https://www.youtube.com/watch?v=h4_AEybOuAY"
  },
  {
    "id": "cNoyUfMCI9c",
    "title": "Subway surfers Part66|Ending Point",
    "duration": 24,
    "url": "https://www.youtube.com/watch?v=cNoyUfMCI9c"
  },
  {
    "id": "p0eoa_c49pA",
    "title": "subway surfers new game shorts video #shorts #trending #gaming #subwaysurfers",
    "duration": 15,
    "url": "https://www.youtube.com/watch?v=p0eoa_c49pA"
  },
  {
    "id": "j3uOUy-GrUY",
    "title": "subway surfers new video #trending",
    "duration": 15,
    "url": "https://www.youtube.com/watch?v=j3uOUy-GrUY"
  },
  {
    "id": "h5Cqy6qGQos",
    "title": "SUBWAY SURF \ud83c\udfc4\u200d\u2640\ufe0f \ud83c\udf0a \ud83d\ude0b \ud83d\ude0d \ud83d\udc4c \ud83c\udfc4\u200d\u2642\ufe0f #gaming #viralpage #game #gameplay #subwaysurfer #game #shortsvideo",
    "duration": 11,
    "url": "https://www.youtube.com/watch?v=h5Cqy6qGQos"
  },
  {
    "id": "dJuAdbofajM",
    "title": "SUBWAY SUFFER FINAL CHAPTER!!! (Indie Horror) - Full Game - No Commentary",
    "duration": 617,
    "url": "https://www.youtube.com/watch?v=dJuAdbofajM"
  },
  {
    "id": "REuKymvrrqk",
    "title": "2 Hours of Relaxing Minecraft Parkour (Scenic, Ambient, Download)",
    "duration": 7201,
    "url": "https://www.youtube.com/watch?v=REuKymvrrqk"
  },
  {
    "id": "C5YR7RwVbMc",
    "title": "Subway Surfers Gameplay | Epic Run ..",
    "duration": 60,
    "url": "https://www.youtube.com/watch?v=C5YR7RwVbMc"
  },
  {
    "id": "vuevUJcu3C4",
    "title": "subway surfers\ud83d\ude87 shorts games video #shorts #trending #gaming #subwaysurfers",
    "duration": 13,
    "url": "https://www.youtube.com/watch?v=vuevUJcu3C4"
  },
  {
    "id": "c6J3qBT0AXo",
    "title": "Playing VALORANT For 10 Hours (No Commentary) | Full Gameplay Walkthrough for all Maps",
    "duration": 36022,
    "url": "https://www.youtube.com/watch?v=c6J3qBT0AXo"
  },
  {
    "id": "dq_tIY8jnHs",
    "title": "Subway Surfers Gameplay Walkthrough Part 4 (Android/iOS)",
    "duration": 1122,
    "url": "https://www.youtube.com/watch?v=dq_tIY8jnHs"
  },
  {
    "id": "37vUvJWna1g",
    "title": "Subway surfers New update \ud83d\ude0d|| Jan 2025 || #subwaysufers #shorts #victoryanthem",
    "duration": 31,
    "url": "https://www.youtube.com/watch?v=37vUvJWna1g"
  },
  {
    "id": "IO8PLtSi3ig",
    "title": "Subway Surfers All Levels Gameplay #Shorts",
    "duration": 27,
    "url": "https://www.youtube.com/watch?v=IO8PLtSi3ig"
  },
  {
    "id": "8UOyNgHS2dM",
    "title": "Subway Surfers All Levels Gameplay #Shorts",
    "duration": 21,
    "url": "https://www.youtube.com/watch?v=8UOyNgHS2dM"
  },
  {
    "id": "cm7Ev-n_EFo",
    "title": "Epic Endless Runner Marathon:\ud83d\udd25 Temple Run 2, Sonic Dash & Subway Surfers Long Gameplay No Commentary",
    "duration": 709,
    "url": "https://www.youtube.com/watch?v=cm7Ev-n_EFo"
  },
  {
    "id": "C2InwQ23jE4",
    "title": "Subway Surfers Gameplay | Subway Surfers World Tour 2025 | High Score Run",
    "duration": 110,
    "url": "https://www.youtube.com/watch?v=C2InwQ23jE4"
  },
  {
    "id": "GGT2j6kRRd4",
    "title": "He rage baited an NPC \ud83d\ude02\ud83d\udc80",
    "duration": 28,
    "url": "https://www.youtube.com/watch?v=GGT2j6kRRd4"
  },
  {
    "id": "kBYtRGN0w7o",
    "title": "Subway Gaming #foryou #viralvideo #subwaysurfers",
    "duration": 22,
    "url": "https://www.youtube.com/watch?v=kBYtRGN0w7o"
  },
  {
    "id": "trHWm6My5DU",
    "title": "Subway Surfers \ud83c\udfc3\ud83d\ude87 Gameplay walkthrough Android,ios BIG UPDATE!!! #gameplay #mobilegame #shorts",
    "duration": 36,
    "url": "https://www.youtube.com/watch?v=trHWm6My5DU"
  },
  {
    "id": "93pAPSS1QVM",
    "title": "Subway Surfers All Levels Gameplay #Shorts",
    "duration": 8,
    "url": "https://www.youtube.com/watch?v=93pAPSS1QVM"
  },
  {
    "id": "ctxj9DTn_Kw",
    "title": "Subway Surfers in Minecraft be like...",
    "duration": 28,
    "url": "https://www.youtube.com/watch?v=ctxj9DTn_Kw"
  },
  {
    "id": "x47rTSkSKRQ",
    "title": "Subway Surfers x Brawl Stars - NEW GAME MODE! \"SHOWDOWN\" - Gameplay (Android)",
    "duration": 481,
    "url": "https://www.youtube.com/watch?v=x47rTSkSKRQ"
  },
  {
    "id": "iOTRdTeblZ4",
    "title": "subway surfers new game video #shorts #trending #gaming #subwaysurfers",
    "duration": 17,
    "url": "https://www.youtube.com/watch?v=iOTRdTeblZ4"
  },
  {
    "id": "CW32NvlVDl4",
    "title": "SUBWAY SUFFER CHAPTER 2!!! (Indie Horror) - Full Game - No Commentary",
    "duration": 649,
    "url": "https://www.youtube.com/watch?v=CW32NvlVDl4"
  },
  {
    "id": "-jcs5UCVRHM",
    "title": "Subway Surfers All Levels Gameplay #Shorts",
    "duration": 14,
    "url": "https://www.youtube.com/watch?v=-jcs5UCVRHM"
  },
  {
    "id": "rnzIZU0eYvM",
    "title": "Subway Surfers\ud83c\udfc3\ud83d\ude87New Version Gameplay walkthrough Android,ios BIG UPDATE!!! subscribe now #shorts",
    "duration": 54,
    "url": "https://www.youtube.com/watch?v=rnzIZU0eYvM"
  },
  {
    "id": "Yw14T0ffPlk",
    "title": "Among Us GamePlay [Among Us No Commentary]",
    "duration": 30,
    "url": "https://www.youtube.com/watch?v=Yw14T0ffPlk"
  },
  {
    "id": "Sqd8CVQRb3g",
    "title": "\ud83c\udfc6 World\u2011Tour City Shuffle in Subway Surfers Gameplay! #shorts",
    "duration": 19,
    "url": "https://www.youtube.com/watch?v=Sqd8CVQRb3g"
  },
  {
    "id": "NyCHIq2nzz0",
    "title": "Hard Level - Subway surfers  #subwaysurfers #subwaycity #subwaysurfers2 #failsvideo #funnyvideos",
    "duration": 19,
    "url": "https://www.youtube.com/watch?v=NyCHIq2nzz0"
  }
]